py_simple_search/__init__.py
py_simple_search/cli.py
py_simple_search/py.typed
py_simple_search-0.0.1a0.dist-info/METADATA
py_simple_search-0.0.1a0.dist-info/WHEEL
py_simple_search-0.0.1a0.dist-info/entry_points.txt
py_simple_search-0.0.1a0.dist-info/top_level.txt
py_simple_search-0.0.1a0.dist-info/RECORD
