Metadata-Version: 2.4
Name: py-simple-search
Version: 0.0.1a0
Summary: This is the Python package py-simple-search.
Author-email: Tony Lee <iamtonylee@gmail.com>
License: MIT
Project-URL: Homepage, https://github.com/hktonylee/py-simple-search
Project-URL: Repository, https://github.com/hktonylee/py-simple-search
Classifier: Programming Language :: Python :: 3
Classifier: Development Status :: 3 - Alpha
Requires-Python: >=3.8
Provides-Extra: dev
Requires-Dist: pytest; extra == "dev"
